ncexplorer/__init__.py
ncexplorer/app.py
ncexplorer/config.py
ncexplorer/const.py
ncexplorer/repository.py
ncexplorer/util.py
ncexplorer/frame/__init__.py
ncexplorer/frame/base.py
ncexplorer/frame/console.py
ncexplorer/frame/flaskgateway.py
ncexplorer/frame/tk.py
ncexplorer/plotter/__init__.py
ncexplorer/plotter/basemapplotter.py
ncexplorer/plotter/canvas.py
ncexplorer/plotter/plotter.py
ncexplorer/plotter/projection.py
ncexplorer/plotter/taylor.py
ncexplorer/test/__init__.py
ncexplorer/test/test_app.py
ncexplorer-0.0.1.dev5.dist-info/DESCRIPTION.rst
ncexplorer-0.0.1.dev5.dist-info/METADATA
ncexplorer-0.0.1.dev5.dist-info/RECORD
ncexplorer-0.0.1.dev5.dist-info/WHEEL
ncexplorer-0.0.1.dev5.dist-info/metadata.json
ncexplorer-0.0.1.dev5.dist-info/top_level.txt
